[
    {
        "url": "https://www.cnn.com/2016/09/20/politics/california-u-2-crash/index.html",
        "title": "U-2 goes down in California; 1 pilot killed",
        "authors": [
            {
                "name": "Barbara Starr",
                "link": null
            },
            {
                "name": "Joe Sterling",
                "link": null
            }
        ],
        "publisher": "www.cnn.com",
        "publish_date": "2016-09-20",
        "text": "By Joe Sterling and Barbara Starr, CNN\nUpdated 7:05 PM ET, Tue September 20, 2016\nChat with us in Facebook Messenger. Find out what's happening in the world as it unfolds.\nJUST WATCHED\n1 dead, 1 injured in California U-2 plane crash 00:45\nStory highlights\nThe crash occurred in Sutter County north of Sacramento\n(CNN)\nOne pilot died and another was injured Tuesday when an Air Force U-2 Dragon Lady crashed shortly after takeoff in northern California, the U.S. Air Force said.\nThe crash occurred about 9:05 a.m. north of Sacramento in Sutter County; TV images showed a brush fire.\nThe aircraft had been assigned to 1st Reconnaissance Squadron at Beale Air Force Base, east of Marysville, and was on a training mission.\nA Unites States Air Force U-2 Dragon Lady crashed shortly after takeoff at approximately 9:05 a.m. today near the... https://t.co/kbjA9snAep\nThe crash occurred near the Sutter Buttes mountain range.\nThe pilots ejected from the aircraft. The incident is under investigation.\nRead More\nCNN affiliate KCRA-TV said people told the station's Mike Luery they saw two parachutes carrying people and a third with equipment.\nU-2 plane crashes in Sutter Buttes; 2 pilots eject https://t.co/Nkf2mRnWZW pic.twitter.com/tAJfRYa16l\nThe U-2 Dragon Lady \"provides high-altitude, all-weather surveillance and reconnaissance, day or night, in direct support of U.S. and allied forces,\" according to an Air Force fact sheet .\nBeale is the home of the 9th Reconnaissance Wing and houses the U-2 Dragon Lady aircraft.\nU-2 history\nIn 1996, a U-2 plane from Beale \"crashed into the parking lot of the Oroville Mercury Register after declaring an inflight emergency 15 minutes after take off,\" KCRA reported. A pilot ejected before the crash and was found dead. A civilian also died.\nA U-2 spy plane was involved in one of the most dramatic incidents of the Cold War.  In 1960, a U-2 was shot down over the Soviet Union during a reconnaissance mission.\nThe American pilot, Francis Gary Powers , spent 21 months in a Moscow prison. He was returned to the United States in 1962 after a spy exchange.\nCNN's Salim Essaid contributed to this report.\n",
        "quotes": [
            [
                "provides high-altitude, all-weather surveillance and reconnaissance, day or night, in direct support of U.S. and allied forces,",
                "",
                false
            ],
            [
                "crashed into the parking lot of the Oroville Mercury Register after declaring an inflight emergency 15 minutes after take off,",
                "Beale",
                false
            ]
        ],
        "links": {
            "articles": [
                "https://www.beale.af.mil/News/Article-Display/Article/933049/1000th-pilot-tames-u-2-dragon-lady/",
                "https://www.kcra.com/article/1-pilot-killed-1-hurt-in-u-2-plane-crash-in-sutter-buttes/6502395",
                "https://www.cnn.com/2012/06/09/us/silver-star-award/",
                "https://www.cnn.com/2014/06/05/us/cold-war-5-things/",
                "https://t.co/Nkf2mRnWZW"
            ],
            "gov_pgs": [],
            "unsure": [
                "https://www.af.mil/About-Us/Fact-Sheets/Display/Article/104560/u-2stu-2s/",
                "https://t.co/kbjA9snAep",
                "https://t.co/tAJfRYa16l"
            ]
        },
        "key_words": [
            "u2",
            "pilot",
            "occurred",
            "air",
            "shortly",
            "killed",
            "crash",
            "takeoff",
            "north",
            "near",
            "force",
            "goes",
            "sutter",
            "california"
        ]
    }
]